cobra_orm/__init__.py
cobra_orm/_core.py
cobra_orm/_utils.py
cobra_orm/errors.py
cobra_orm-0.1.1.dist-info/LICENSE.txt
cobra_orm-0.1.1.dist-info/METADATA
cobra_orm-0.1.1.dist-info/WHEEL
cobra_orm-0.1.1.dist-info/RECORD
