Metadata-Version: 2.1
Name: cobra-orm
Version: 0.1.1
Summary: A simple asynchronous ORM for aiosqlite with extensive type hinting.
Home-page: https://github.com/TitaniumBrain/cobra-orm
Author: TitaniumBrain
Author-email: titaniumbrain@vivaldi.net
Requires-Python: >=3.11,<4.0
Classifier: Programming Language :: Python :: 3
Classifier: Programming Language :: Python :: 3.11
Classifier: Programming Language :: Python :: 3.12
Requires-Dist: aiosqlite (>=0.19.0,<0.20.0)
Project-URL: Repository, https://github.com/TitaniumBrain/cobra-orm
